[
  {
    "이슈": "아레나 수치",
    "날짜": "2026-06-24 07:23",
    "수집건수": 84,
    "주요_동향": "부정",
    "동향_요약": "아레나 수치 오류와 관련하여 제시된 보상안에 대한 불만족이 극에 달해 있으며, 대부분의 이용자들이 전액 환불을 요구하고 있습니다. 게임 운영진에 대한 불신이 심화되어 소비자기관 신고 및 조직적인 항의 움직임이 활발하게 나타나고 있습니다.",
    "긍정_반응": "없음",
    "부정_반응": "제시된 보상(어빌 10만개, 스타포스 등)이 터무니없고 부족하다고 비판하며 전액 환불을 강력히 요구하고 있습니다. '유저 기망', '사기 게임' 등 운영에 대한 극심한 불신을 표출하고 있으며, 소보원, 공정위, 신문고 등 외부 기관을 통한 적극적인 신고 및 제재를 촉구하는 정보 공유가 활발합니다. 또한 '⬤▅▇█▇▆▅▄▇'와 같은 상징적인 문구를 사용하며 집단 행동을 독려하고 있습니다.",
    "주요_키워드": [
      "환불",
      "아레나",
      "버그",
      "신고",
      "보상",
      "수치",
      "기망",
      "공정위",
      "소보원",
      "신뢰"
    ],
    "대표_반응": [
      "신고용 공지스샷, 신고작성글",
      "메숭이들아 구멍가게 상대하냐 더 확실한 논리를 만들면 충분하다 가자 환불",
      "⬤▅▇█▇▆▅▄▇ 환불하자"
    ],
    "분석_근거": "대부분의 게시글이 아레나 수치 오류 관련 '환불', '신고', '보상 불만', '운영 불신'을 다루고 있으며, 높은 추천수와 조회수를 기록한 글들이 이러한 부정적 여론 형성에 큰 영향을 미치고 있기 때문입니다. 집단 항의를 나타내는 상징적인 문구의 반복 사용 또한 부정적 동향의 강력한 근거입니다."
  }
]